{"last_node_id": 44, "last_link_id": 68, "nodes": [{"id": 29, "type": "GroundingDinoSAMSegment (segment anything)", "pos": [749, 640], "size": {"0": 352.79998779296875, "1": 124.0001220703125}, "flags": {}, "order": 5, "mode": 0, "inputs": [{"name": "sam_model", "type": "SAM_MODEL", "link": 55}, {"name": "grounding_dino_model", "type": "GROUNDING_DINO_MODEL", "link": 56}, {"name": "image", "type": "IMAGE", "link": 57}], "outputs": [{"name": "IMAGE", "type": "IMAGE", "links": [], "shape": 3, "slot_index": 0}, {"name": "MASK", "type": "MASK", "links": [59, 61], "shape": 3, "slot_index": 1}], "properties": {"Node name for S&R": "GroundingDinoSAMSegment (segment anything)"}, "widgets_values": ["cake", 0.3]}, {"id": 27, "type": "GroundingDinoModelLoader (segment anything)", "pos": [45, 1126], "size": {"0": 532.800048828125, "1": 104.4000244140625}, "flags": {}, "order": 2, "mode": 0, "outputs": [{"name": "GROUNDING_DINO_MODEL", "type": "GROUNDING_DINO_MODEL", "links": [56], "shape": 3, "slot_index": 0}], "properties": {"Node name for S&R": "GroundingDinoModelLoader (segment anything)"}, "widgets_values": ["GroundingDINO_SwinT_OGC (694MB)"]}, {"id": 28, "type": "SAMModelLoader (segment anything)", "pos": [254, 1014], "size": {"0": 315, "1": 58}, "flags": {}, "order": 1, "mode": 0, "outputs": [{"name": "SAM_MODEL", "type": "SAM_MODEL", "links": [55], "shape": 3, "slot_index": 0}], "properties": {"Node name for S&R": "SAMModelLoader (segment anything)"}, "widgets_values": ["sam_vit_h (2.56GB)"]}, {"id": 1, "type": "LoadImage", "pos": [101, 386], "size": [470.19439697265625, 578.6853942871094], "flags": {}, "order": 3, "mode": 0, "outputs": [{"name": "IMAGE", "type": "IMAGE", "links": [52, 57], "shape": 3, "slot_index": 0}, {"name": "MASK", "type": "MASK", "links": null, "shape": 3, "slot_index": 1}], "properties": {"Node name for S&R": "LoadImage"}, "widgets_values": ["test_image.jpg", "image"]}, {"id": 24, "type": "BrushNetLoader", "pos": [222, 260], "size": {"0": 354.79998779296875, "1": 61.60003662109375}, "flags": {}, "order": 0, "mode": 0, "outputs": [{"name": "BrushNet", "type": "BRMODEL", "links": [67], "shape": 3, "slot_index": 0}], "properties": {"Node name for S&R": "BrushNetLoader"}, "widgets_values": ["brushnet/random_mask_brushnet_ckpt"]}, {"id": 44, "type": "BrushNetPipeline", "pos": [704, 263], "size": [371.60003662109375, 103.20001220703125], "flags": {}, "order": 4, "mode": 0, "inputs": [{"name": "brushnet", "type": "BRMODEL", "link": 67}], "outputs": [{"name": "BRPL", "type": "BRPL", "links": [66], "shape": 3, "slot_index": 0}], "properties": {"Node name for S&R": "BrushNetPipeline"}, "widgets_values": ["realisticVisionV60B1_v51VAE.safetensors"]}, {"id": 26, "type": "BrushNetInpaint", "pos": [1254, 411], "size": {"0": 315, "1": 194}, "flags": {}, "order": 7, "mode": 0, "inputs": [{"name": "BRPL", "type": "BRPL", "link": 66}, {"name": "image", "type": "IMAGE", "link": 52}, {"name": "mask", "type": "MASK", "link": 61}], "outputs": [{"name": "Image", "type": "IMAGE", "links": [53], "shape": 3, "slot_index": 0}], "properties": {"Node name for S&R": "BrushNetInpaint"}, "widgets_values": ["burger", 0, "fixed", 30, 1]}, {"id": 12, "type": "PreviewImage", "pos": [1634, 411], "size": [523.5944213867188, 547.4853210449219], "flags": {}, "order": 9, "mode": 0, "inputs": [{"name": "images", "type": "IMAGE", "link": 53}], "properties": {"Node name for S&R": "PreviewImage"}}, {"id": 32, "type": "PreviewImage", "pos": [1386, 711], "size": {"0": 210, "1": 246}, "flags": {}, "order": 8, "mode": 0, "inputs": [{"name": "images", "type": "IMAGE", "link": 60}], "properties": {"Node name for S&R": "PreviewImage"}}, {"id": 31, "type": "MaskToImage", "pos": [1140, 711], "size": {"0": 210, "1": 26}, "flags": {}, "order": 6, "mode": 0, "inputs": [{"name": "mask", "type": "MASK", "link": 59}], "outputs": [{"name": "IMAGE", "type": "IMAGE", "links": [60], "shape": 3, "slot_index": 0}], "properties": {"Node name for S&R": "MaskToImage"}}], "links": [[52, 1, 0, 26, 1, "IMAGE"], [53, 26, 0, 12, 0, "IMAGE"], [55, 28, 0, 29, 0, "SAM_MODEL"], [56, 27, 0, 29, 1, "GROUNDING_DINO_MODEL"], [57, 1, 0, 29, 2, "IMAGE"], [59, 29, 1, 31, 0, "MASK"], [60, 31, 0, 32, 0, "IMAGE"], [61, 29, 1, 26, 2, "MASK"], [66, 44, 0, 26, 0, "BRPL"], [67, 24, 0, 44, 0, "BRMODEL"]], "groups": [], "config": {}, "extra": {}, "version": 0.4}